{
    "id": "166470-0031-07",
    "text": "En diezynuebe de Julio de mil ochocientoscuarenta; yo Don Antonio Loreto Sanchez Presbitero cura beneficiado por Su Majestad de la Iglesia Parroquial de la Purisima Concepción de esta villa de Cienfuegos en ella y su jurisdiccion vicario Eclesiastico por Santa Eclesiastica Illustrisima bauticé solemnemente y puse los santos oleos a una negra adulta natural de Africa, de la propiedad de Don Juan Vives, en cuya negra ejerci las sacras ceremonias y preces y la puse por nombre Dominga fue su madrina Isabel aquien adverti el parentesco espiritual y demas obligaciones y lo firmé",
    "people": [
      {
        "id": "166470-0031-07-01",
        "name": "Antonio Loreto Sanchez",
        "indices": [[13, 37]],
        "origin": null,
        "ethnicities": null,
        "age": null,
        "legitimacy": null,
        "occupation": "Presbitero cura beneficiado",
        "phenotype": null,
        "status": "free",
        "titles": ["Don"],
        "ranks": ["Eclesiastico"],
        "relationships": []
      },
      {
        "id": "166470-0031-07-02",
        "name": "Dominga",
        "indices": [[205, 212]],
        "origin": "Africa",
        "ethnicities": null,
        "age": "adulta",
        "legitimacy": null,
        "occupation": null,
        "phenotype": null,
        "status": "enslaved",
        "titles": [],
        "ranks": null,
        "relationships": [
          {"related_person": "166470-0031-07-04", "relationship_type": "godmother"},
          {"related_person": "166470-0031-07-03", "relationship_type": "enslaver"}
        ]
      },
      {
        "id": "166470-0031-07-03",
        "name": "Juan Vives",
        "indices": [[175, 186]],
        "origin": null,
        "ethnicities": null,
        "age": null,
        "legitimacy": null,
        "occupation": null,
        "phenotype": null,
        "status": "free",
        "titles": ["Don"],
        "ranks": null,
        "relationships": [
          {"related_person": "166470-0031-07-02", "relationship_type": "slave"}
        ]
      },
      {
        "id": "166470-0031-07-04",
        "name": "Isabel",
        "indices": [[243, 249]],
        "origin": null,
        "ethnicities": null,
        "age": null,
        "legitimacy": null,
        "occupation": null,
        "phenotype": null,
        "status": null,
        "titles": [],
        "ranks": null,
        "relationships": [
          {"related_person": "166470-0031-07-02", "relationship_type": "godchild"}
        ]
      }
    ],
    "places": [
      {
        "id": "166470-0031-07-L01",
        "name": "Cienfuegos",
        "indices": [[91, 101]]
      },
      {
        "id": "166470-0031-07-L02",
        "name": "Africa",
        "indices": [[153, 159]]
      },
      {
        "id": "166470-0031-07-L03",
        "name": "Iglesia de la Purisima Concepcion",
        "indices": [[70, 101]]
      }
    ],
    "events": [
      {
        "id": "166470-0031-07-E01",
        "type": "baptism",
        "principal": "166470-0031-07-02",
        "date": "1840-07-19",
        "location": "166470-0031-07-L03",
        "cleric": "166470-0031-07-01"
      }
    ]
  }
  